<?xml version='1.0' encoding='ISO-8859-1' ?>

<picture version='3' xmlns:rgml='http://r-project.org/RGML' source='logo.ps' date='2013-12-31 17:50:08' creator='R (3.0.2)' >

<path type='fill' id='1'>
	<context>
		<rgb r='0.4' g='0.4' b='0.4'/>
		<style lwd='10.0' lty='' lineend='0' linemitre='10.0' linejoin='0'/>
	</context>

	<move y='1447.57' x='228.52'/>
	<line y='1357.45' x='259.531'/>
	<line y='1357.45' x='353.871'/>
	<line y='1299.48' x='278.672'/>
	<line y='1209.13' x='305.98'/>
	<line y='1263.04' x='228.52'/>
	<line y='1209.13' x='151.051'/>
	<line y='1299.48' x='178.398'/>
	<line y='1357.45' x='103.199'/>
	<line y='1357.45' x='197.539'/>
	<line y='1447.57' x='228.52'/>
	<move y='1447.57' x='228.52'/>
</path>

<path type='fill' id='2'>
	<context>
		<rgb r='0.4' g='0.4' b='0.4'/>
		<style lwd='10.0' lty='' lineend='0' linemitre='10.0' linejoin='0'/>
	</context>

	<move y='1743.54' x='531.02'/>
	<line y='1651.86' x='557.148'/>
	<line y='1646.82' x='651.371'/>
	<line y='1592.92' x='573.121'/>
	<line y='1501.32' x='595.621'/>
	<line y='1559.25' x='521.129'/>
	<line y='1509.56' x='440.898'/>
	<line y='1598.31' x='473.051'/>
	<line y='1660.26' x='401.02'/>
	<line y='1655.18' x='495.27'/>
	<line y='1743.54' x='531.02'/>
	<move y='1743.54' x='531.02'/>
</path>

<path type='fill' id='3'>
	<context>
		<rgb r='0.4' g='0.4' b='0.4'/>
		<style lwd='10.0' lty='' lineend='0' linemitre='10.0' linejoin='0'/>
	</context>

	<move y='1849.83' x='932.34'/>
	<line y='1759.71' x='963.32'/>
	<line y='1759.71' x='1057.7'/>
	<line y='1701.75' x='982.5'/>
	<line y='1611.39' x='1009.8'/>
	<line y='1665.3' x='932.34'/>
	<line y='1611.39' x='854.879'/>
	<line y='1701.75' x='882.23'/>
	<line y='1759.71' x='806.988'/>
	<line y='1759.71' x='901.371'/>
	<line y='1849.83' x='932.34'/>
	<move y='1849.83' x='932.34'/>
</path>

<path type='fill' id='4'>
	<context>
		<rgb r='0.4' g='0.4' b='0.4'/>
		<style lwd='10.0' lty='' lineend='0' linemitre='10.0' linejoin='0'/>
	</context>

	<move y='1741.98' x='1334.73'/>
	<line y='1651.86' x='1365.78'/>
	<line y='1651.86' x='1460.08'/>
	<line y='1593.89' x='1384.92'/>
	<line y='1503.54' x='1412.27'/>
	<line y='1557.45' x='1334.73'/>
	<line y='1503.54' x='1257.34'/>
	<line y='1593.89' x='1284.61'/>
	<line y='1651.86' x='1209.41'/>
	<line y='1651.86' x='1303.75'/>
	<line y='1741.98' x='1334.73'/>
	<move y='1741.98' x='1334.73'/>
</path>

<path type='fill' id='5'>
	<context>
		<rgb r='0.4' g='0.4' b='0.4'/>
		<style lwd='10.0' lty='' lineend='0' linemitre='10.0' linejoin='0'/>
	</context>

	<move y='1443.97' x='1630.78'/>
	<line y='1353.86' x='1661.76'/>
	<line y='1353.86' x='1756.17'/>
	<line y='1295.89' x='1680.98'/>
	<line y='1205.57' x='1708.32'/>
	<line y='1259.44' x='1630.78'/>
	<line y='1205.57' x='1553.36'/>
	<line y='1295.89' x='1580.7'/>
	<line y='1353.86' x='1505.51'/>
	<line y='1353.86' x='1599.88'/>
	<line y='1443.97' x='1630.78'/>
	<move y='1443.97' x='1630.78'/>
</path>

<path type='fill' id='6'>
	<context>
		<rgb r='0.4' g='0.4' b='0.4'/>
		<style lwd='10.0' lty='' lineend='0' linemitre='10.0' linejoin='0'/>
	</context>

	<move y='1047.29' x='1737.27'/>
	<line y='957.18' x='1768.24'/>
	<line y='957.18' x='1862.58'/>
	<line y='899.211' x='1787.38'/>
	<line y='808.859' x='1814.77'/>
	<line y='862.762' x='1737.27'/>
	<line y='808.859' x='1659.77'/>
	<line y='899.211' x='1687.11'/>
	<line y='957.18' x='1611.91'/>
	<line y='957.18' x='1706.29'/>
	<line y='1047.29' x='1737.27'/>
	<move y='1047.29' x='1737.27'/>
</path>

<path type='fill' id='7'>
	<context>
		<rgb r='0.4' g='0.4' b='0.4'/>
		<style lwd='10.0' lty='' lineend='0' linemitre='10.0' linejoin='0'/>
	</context>

	<move y='640.93' x='1628.87'/>
	<line y='550.77' x='1659.88'/>
	<line y='550.77' x='1754.26'/>
	<line y='492.84' x='1679.06'/>
	<line y='402.531' x='1706.33'/>
	<line y='456.43' x='1628.87'/>
	<line y='402.531' x='1551.45'/>
	<line y='492.84' x='1578.79'/>
	<line y='550.77' x='1503.52'/>
	<line y='550.77' x='1597.93'/>
	<line y='640.93' x='1628.87'/>
	<move y='640.93' x='1628.87'/>
</path>

<path type='fill' id='8'>
	<context>
		<rgb r='0.4' g='0.4' b='0.4'/>
		<style lwd='10.0' lty='' lineend='0' linemitre='10.0' linejoin='0'/>
	</context>

	<move y='346.789' x='1330.9'/>
	<line y='256.711' x='1361.88'/>
	<line y='256.711' x='1456.25'/>
	<line y='198.738' x='1381.02'/>
	<line y='108.391' x='1408.32'/>
	<line y='162.25' x='1330.9'/>
	<line y='108.391' x='1253.44'/>
	<line y='198.738' x='1280.78'/>
	<line y='256.711' x='1205.59'/>
	<line y='256.711' x='1299.92'/>
	<line y='346.789' x='1330.9'/>
	<move y='346.789' x='1330.9'/>
</path>

<path type='fill' id='9'>
	<context>
		<rgb r='0.4' g='0.4' b='0.4'/>
		<style lwd='10.0' lty='' lineend='0' linemitre='10.0' linejoin='0'/>
	</context>

	<move y='238.461' x='930.309'/>
	<line y='148.309' x='961.328'/>
	<line y='148.309' x='1055.66'/>
	<line y='90.3789' x='980.469'/>
	<line y='-0.0117188' x='1007.77'/>
	<line y='53.9297' x='930.309'/>
	<line y='-0.0117188' x='852.891'/>
	<line y='90.3789' x='880.23'/>
	<line y='148.309' x='804.961'/>
	<line y='148.309' x='899.379'/>
	<line y='238.461' x='930.309'/>
	<move y='238.461' x='930.309'/>
</path>

<path type='fill' id='10'>
	<context>
		<rgb r='0.4' g='0.4' b='0.4'/>
		<style lwd='10.0' lty='' lineend='0' linemitre='10.0' linejoin='0'/>
	</context>

	<move y='342.922' x='527.809'/>
	<line y='252.84' x='558.789'/>
	<line y='252.84' x='653.16'/>
	<line y='194.828' x='577.969'/>
	<line y='104.52' x='605.309'/>
	<line y='158.43' x='527.809'/>
	<line y='104.52' x='450.391'/>
	<line y='194.828' x='477.699'/>
	<line y='252.84' x='402.461'/>
	<line y='252.84' x='496.879'/>
	<line y='342.922' x='527.809'/>
	<move y='342.922' x='527.809'/>
</path>

<path type='fill' id='11'>
	<context>
		<rgb r='0.4' g='0.4' b='0.4'/>
		<style lwd='10.0' lty='' lineend='0' linemitre='10.0' linejoin='0'/>
	</context>

	<move y='642.879' x='233.711'/>
	<line y='552.719' x='264.691'/>
	<line y='552.719' x='359.059'/>
	<line y='494.75' x='283.871'/>
	<line y='404.441' x='311.129'/>
	<line y='458.352' x='233.711'/>
	<line y='404.441' x='156.25'/>
	<line y='494.75' x='183.59'/>
	<line y='552.719' x='108.359'/>
	<line y='552.719' x='202.73'/>
	<line y='642.879' x='233.711'/>
	<move y='642.879' x='233.711'/>
</path>

<path type='fill' id='12'>
	<context>
		<rgb r='0.4' g='0.4' b='0.4'/>
		<style lwd='10.0' lty='' lineend='0' linemitre='10.0' linejoin='0'/>
	</context>

	<move y='1045.34' x='125.309'/>
	<line y='955.262' x='156.328'/>
	<line y='955.262' x='250.699'/>
	<line y='897.25' x='175.469'/>
	<line y='806.941' x='202.809'/>
	<line y='860.852' x='125.309'/>
	<line y='806.941' x='47.8906'/>
	<line y='897.25' x='75.2305'/>
	<line y='955.262' x='0.0'/>
	<line y='955.262' x='94.3398'/>
	<line y='1045.34' x='125.309'/>
	<move y='1045.34' x='125.309'/>
</path>

<path type='fill' id='13'>
	<context>
		<rgb r='0.4' g='0.4' b='0.4'/>
		<style lwd='10.0' lty='' lineend='0' linemitre='10.0' linejoin='0'/>
	</context>

	<move y='790.5' x='796.051'/>
	<line y='894.012' x='899.57'/>
	<line y='930.961' x='862.578'/>
	<line y='1152.57' x='1084.14'/>
	<line y='931.98' x='1304.77'/>
	<line y='712.289' x='1085.12'/>
	<line y='746.16' x='1051.29'/>
	<line y='640.691' x='945.781'/>
	<line y='562.328' x='1024.18'/>
	<line y='561.316' x='1025.26'/>
	<line y='558.656' x='1028.43'/>
	<line y='554.883' x='1033.54'/>
	<line y='550.539' x='1040.48'/>
	<line y='546.172' x='1049.1'/>
	<line y='542.324' x='1059.28'/>
	<line y='539.535' x='1070.88'/>
	<line y='538.352' x='1083.79'/>
	<line y='539.188' x='1096.89'/>
	<line y='541.812' x='1109.02'/>
	<line y='545.641' x='1119.93'/>
	<line y='550.086' x='1129.4'/>
	<line y='554.562' x='1137.18'/>
	<line y='558.484' x='1143.04'/>
	<line y='561.27' x='1146.73'/>
	<line y='562.328' x='1148.01'/>
	<line y='874.828' x='1460.55'/>
	<line y='875.867' x='1461.36'/>
	<line y='878.891' x='1463.5'/>
	<line y='883.734' x='1466.53'/>
	<line y='890.238' x='1470.02'/>
	<line y='898.242' x='1473.52'/>
	<line y='907.59' x='1476.6'/>
	<line y='918.121' x='1478.81'/>
	<line y='929.68' x='1479.73'/>
	<line y='941.523' x='1478.87'/>
	<line y='952.793' x='1476.42'/>
	<line y='963.188' x='1472.9'/>
	<line y='972.383' x='1468.84'/>
	<line y='980.078' x='1464.77'/>
	<line y='985.961' x='1461.21'/>
	<line y='989.715' x='1458.69'/>
	<line y='991.039' x='1457.73'/>
	<line y='1297.14' x='1151.76'/>
	<line y='1298.29' x='1150.52'/>
	<line y='1301.31' x='1146.95'/>
	<line y='1305.59' x='1141.23'/>
	<line y='1310.51' x='1133.57'/>
	<line y='1315.44' x='1124.16'/>
	<line y='1319.76' x='1113.21'/>
	<line y='1322.85' x='1100.91'/>
	<line y='1324.09' x='1087.46'/>
	<line y='1323.03' x='1074.04'/>
	<line y='1320.03' x='1061.85'/>
	<line y='1315.71' x='1051.06'/>
	<line y='1310.75' x='1041.84'/>
	<line y='1305.76' x='1034.38'/>
	<line y='1301.4' x='1028.82'/>
	<line y='1298.31' x='1025.37'/>
	<line y='1297.14' x='1024.18'/>
	<line y='981.0' x='708.012'/>
	<line y='979.801' x='707.398'/>
	<line y='976.43' x='705.789'/>
	<line y='971.234' x='703.508'/>
	<line y='964.551' x='700.898'/>
	<line y='956.723' x='698.289'/>
	<line y='948.094' x='696.008'/>
	<line y='939.0' x='694.398'/>
	<line y='929.789' x='693.789'/>
	<line y='919.633' x='694.398'/>
	<line y='910.383' x='696.008'/>
	<line y='902.176' x='698.289'/>
	<line y='895.148' x='700.898'/>
	<line y='889.441' x='703.508'/>
	<line y='885.191' x='705.789'/>
	<line y='882.543' x='707.398'/>
	<line y='881.629' x='708.012'/>
	<line y='790.5' x='796.051'/>
	<line y='790.5' x='796.051'/>
	<move y='790.5' x='796.051'/>
</path>

<path type='fill' id='14'>
	<context>
		<rgb r='0.4' g='0.4' b='0.4'/>
		<style lwd='10.0' lty='' lineend='0' linemitre='10.0' linejoin='0'/>
	</context>

	<move y='966.789' x='954.531'/>
	<line y='1070.89' x='1058.63'/>
	<line y='990.109' x='1138.44'/>
	<line y='989.008' x='1139.32'/>
	<line y='985.816' x='1141.64'/>
	<line y='980.703' x='1144.91'/>
	<line y='973.836' x='1148.68'/>
	<line y='965.379' x='1152.43'/>
	<line y='955.496' x='1155.71'/>
	<line y='944.363' x='1158.03'/>
	<line y='932.141' x='1158.91'/>
	<line y='918.957' x='1157.98'/>
	<line y='907.348' x='1155.55'/>
	<line y='897.363' x='1152.11'/>
	<line y='889.066' x='1148.16'/>
	<line y='882.512' x='1144.22'/>
	<line y='877.762' x='1140.78'/>
	<line y='874.867' x='1138.34'/>
	<line y='873.891' x='1137.42'/>
	<line y='558.93' x='822.5'/>
	<line y='558.074' x='821.582'/>
	<line y='555.82' x='818.848'/>
	<line y='552.637' x='814.316'/>
	<line y='548.988' x='808.012'/>
	<line y='545.34' x='799.949'/>
	<line y='542.156' x='790.148'/>
	<line y='539.902' x='778.637'/>
	<line y='539.051' x='765.43'/>
	<line y='539.957' x='752.574'/>
	<line y='542.355' x='740.973'/>
	<line y='545.746' x='730.762'/>
	<line y='549.633' x='722.09'/>
	<line y='553.52' x='715.098'/>
	<line y='556.91' x='709.926'/>
	<line y='559.309' x='706.719'/>
	<line y='560.219' x='705.621'/>
	<line y='874.75' x='391.09'/>
	<line y='876.09' x='390.258'/>
	<line y='879.836' x='388.066'/>
	<line y='885.578' x='384.973'/>
	<line y='892.898' x='381.426'/>
	<line y='901.383' x='377.875'/>
	<line y='910.625' x='374.781'/>
	<line y='920.203' x='372.59'/>
	<line y='929.711' x='371.762'/>
	<line y='942.133' x='372.66'/>
	<line y='953.621' x='375.031'/>
	<line y='963.949' x='378.383'/>
	<line y='972.902' x='382.23'/>
	<line y='980.25' x='386.074'/>
	<line y='985.773' x='389.426'/>
	<line y='989.25' x='391.797'/>
	<line y='990.461' x='392.699'/>
	<line y='1295.61' x='697.34'/>
	<line y='1296.79' x='698.5'/>
	<line y='1299.92' x='701.898'/>
	<line y='1304.34' x='707.395'/>
	<line y='1309.4' x='714.855'/>
	<line y='1314.46' x='724.145'/>
	<line y='1318.88' x='735.129'/>
	<line y='1322.0' x='747.672'/>
	<line y='1323.19' x='761.641'/>
	<line y='1322.0' x='776.801'/>
	<line y='1318.88' x='789.996'/>
	<line y='1314.46' x='801.199'/>
	<line y='1309.4' x='810.402'/>
	<line y='1304.34' x='817.586'/>
	<line y='1299.92' x='822.738'/>
	<line y='1296.79' x='825.84'/>
	<line y='1295.61' x='826.879'/>
	<line y='1221.16' x='901.289'/>
	<line y='1121.59' x='801.641'/>
	<line y='1155.46' x='767.809'/>
	<line y='930.031' x='542.34'/>
	<line y='708.43' x='763.949'/>
	<line y='932.68' x='988.121'/>
	<line y='966.789' x='954.531'/>
	<line y='966.789' x='954.531'/>
	<move y='966.789' x='954.531'/>
</path>

<summary count='14' ymax='1849.83' ymin='-0.0117188' xmax='1862.58' xmin='0.0'/>

</picture>
